abtrap/__init__.py
abtrap-0.1.1.dist-info/METADATA
abtrap-0.1.1.dist-info/WHEEL
abtrap-0.1.1.dist-info/top_level.txt
abtrap-0.1.1.dist-info/RECORD
