Metadata-Version: 2.1
Name: abtrap
Version: 0.1.1
Summary: AB-TRAP: building invisibility shields to protect network devices
Home-page: https://c2dc.github.io/abtrap
Author: Gustavo Bertoli, Lourenço Pereira, Filipe Verri
Author-email: gubertoli@gmail.com, lourenco.junior@gp.ita.br, filipeverri@gmail.com
License: UNKNOWN
Project-URL: Bug Tracker, https://github.com/c2dc/abtrap/issues
Platform: UNKNOWN
Classifier: Programming Language :: Python :: 3
Classifier: License :: OSI Approved :: MIT License
Classifier: Operating System :: OS Independent
Requires-Python: >=3.6
Requires-Dist: pandas
Requires-Dist: numpy
